setup.cfg
setup.py
extscrape/__init__.py
extscrape/helpers.py
extscrape/main.py
extscrape.egg-info/PKG-INFO
extscrape.egg-info/SOURCES.txt
extscrape.egg-info/dependency_links.txt
extscrape.egg-info/entry_points.txt
extscrape.egg-info/requires.txt
extscrape.egg-info/top_level.txt