Metadata-Version: 1.1
Name: extscrape
Version: 1.0.1
Summary: Scrapes files from the web with specified extensions.
Home-page: https://github.com/parakalan/extscrape
Author: Sudharshan
Author-email: stsudharshan@gmail.com
License: MIT License
Keywords: scrape,extension
Platform: UNKNOWN
Classifier: Operating System :: POSIX :: Linux
Classifier: License :: OSI Approved :: MIT License
Classifier: Programming Language :: Python :: 2.7
Classifier: Topic :: Education
